crashstats_tools/__init__.py
crashstats_tools/cmd_fetch_data.py
crashstats_tools/cmd_reprocess.py
crashstats_tools/cmd_supersearch.py
crashstats_tools/cmd_supersearchfacet.py
crashstats_tools/libcrashstats.py
crashstats_tools/utils.py
crashstats_tools-2.1.0.dist-info/LICENSE
crashstats_tools-2.1.0.dist-info/METADATA
crashstats_tools-2.1.0.dist-info/WHEEL
crashstats_tools-2.1.0.dist-info/entry_points.txt
crashstats_tools-2.1.0.dist-info/top_level.txt
crashstats_tools-2.1.0.dist-info/RECORD
