Metadata-Version: 2.1
Name: crashstats-tools
Version: 2.1.0
Summary: Tools for working with Crash Stats (https://crash-stats.mozilla.org/)
Author: Will Kahn-Greene
License: MPLv2
Project-URL: Homepage, https://github.com/mozilla-services/crashstats-tools
Project-URL: Source, https://github.com/mozilla-services/crashstats-tools
Project-URL: Issues, https://github.com/mozilla-services/crashstats-tools
Keywords: socorro
Classifier: Development Status :: 5 - Production/Stable
Classifier: Intended Audience :: Developers
Classifier: License :: OSI Approved :: Mozilla Public License 2.0 (MPL 2.0)
Classifier: Natural Language :: English
Classifier: Programming Language :: Python :: 3 :: Only
Classifier: Programming Language :: Python :: 3.9
Classifier: Programming Language :: Python :: 3.10
Classifier: Programming Language :: Python :: 3.11
Classifier: Programming Language :: Python :: 3.12
Classifier: Programming Language :: Python :: 3.13
Classifier: Programming Language :: Python :: Implementation :: CPython
Classifier: Topic :: Software Development :: Libraries :: Python Modules
Requires-Python: >=3.9
License-File: LICENSE
Requires-Dist: click
Requires-Dist: more-itertools
Requires-Dist: python-dotenv
Requires-Dist: requests
Requires-Dist: rich
Requires-Dist: tomli >=1.1.0 ; python_version < "3.11"
Provides-Extra: dev
Requires-Dist: build ; extra == 'dev'
Requires-Dist: cogapp ; extra == 'dev'
Requires-Dist: freezegun ; extra == 'dev'
Requires-Dist: pytest ; extra == 'dev'
Requires-Dist: responses ; extra == 'dev'
Requires-Dist: ruff ; extra == 'dev'
Requires-Dist: setuptools ; extra == 'dev'
Requires-Dist: tox ; extra == 'dev'
Requires-Dist: tox-gh-actions ; extra == 'dev'
Requires-Dist: twine ; extra == 'dev'
Requires-Dist: wheel ; extra == 'dev'
